polars_iptools-0.1.10.dist-info/METADATA
polars_iptools-0.1.10.dist-info/WHEEL
polars_iptools-0.1.10.dist-info/licenses/LICENSE
polars_iptools/geoip.py
polars_iptools/iptools.py
polars_iptools/spur.py
polars_iptools/typing.py
polars_iptools/_internal.pyi
polars_iptools/__init__.py
polars_iptools/_internal.pyd
polars_iptools-0.1.10.dist-info/RECORD
