Metadata-Version: 2.4
Name: polars-iptools
Version: 0.1.10
Classifier: Programming Language :: Rust
Classifier: Programming Language :: Python :: Implementation :: CPython
Classifier: Programming Language :: Python :: Implementation :: PyPy
Requires-Dist: polars>=1.3.0
License-File: LICENSE
Summary: Polars extension for IP address parsing and enrichment including geolocation
Keywords: polars,dfir,geoip
License: MIT
Requires-Python: >=3.9
Project-URL: Source Code, https://github.com/erichutchins/polars_iptools
